checkers/__init__.py
checkers/american.py
checkers/base.py
checkers/main.py
checkers/models.py
checkers/move.py
checkers/utils.py
fast_checkers-0.2.0.dist-info/METADATA
fast_checkers-0.2.0.dist-info/WHEEL
fast_checkers-0.2.0.dist-info/top_level.txt
fast_checkers-0.2.0.dist-info/RECORD
