Metadata-Version: 2.1
Name: fast-checkers
Version: 0.2.0
Summary: A checkers library for Python, with move generation and validation, PDN parsing and writing. Supprots multiple variants of game.
Home-page: https://github.com/michalskibinski109/checkers
Author: Michał Skibiński
Author-email: mskibinski109@gmail.com
License: GPL-3.0+
Project-URL: Documentation, https://michalskibinski109.github.io/checkers/index.html
Keywords: checkers AI mini-max droughts,game,board
Classifier: Development Status :: 5 - Production/Stable
Classifier: Intended Audience :: Developers
Classifier: Intended Audience :: Science/Research
Classifier: License :: OSI Approved :: GNU General Public License v3 or later (GPLv3+)
Classifier: Operating System :: OS Independent
Classifier: Programming Language :: Python :: 3 :: Only
Classifier: Programming Language :: Python :: 3.7
Classifier: Programming Language :: Python :: 3.8
Classifier: Programming Language :: Python :: 3.9
Classifier: Programming Language :: Python :: 3.10
Classifier: Programming Language :: Python :: 3.11
Classifier: Topic :: Games/Entertainment :: Board Games
Classifier: Topic :: Games/Entertainment :: Turn Based Strategy
Classifier: Topic :: Software Development :: Libraries :: Python Modules
Classifier: Typing :: Typed
Requires-Python: >=3.10
